py_license_auditor/__init__.py
py_license_auditor/bin/py-license-auditor-linux-aarch64
py_license_auditor/bin/py-license-auditor-linux-x86_64
py_license_auditor/bin/py-license-auditor-macos-aarch64
py_license_auditor/bin/py-license-auditor-macos-x86_64
py_license_auditor-0.6.0.dist-info/licenses/LICENSE-APACHE
py_license_auditor-0.6.0.dist-info/licenses/LICENSE-MIT
py_license_auditor-0.6.0.dist-info/METADATA
py_license_auditor-0.6.0.dist-info/WHEEL
py_license_auditor-0.6.0.dist-info/entry_points.txt
py_license_auditor-0.6.0.dist-info/top_level.txt
py_license_auditor-0.6.0.dist-info/RECORD
