Metadata-Version: 2.4
Name: py-license-auditor
Version: 0.6.0
Summary: Fast license auditor for uv projects - Extract and analyze license information with uv.lock integration
Author-email: yayami3 <116920988+yayami3@users.noreply.github.com>
License: MIT OR Apache-2.0
Project-URL: Homepage, https://github.com/yayami3/py-license-auditor
Project-URL: Repository, https://github.com/yayami3/py-license-auditor
Project-URL: Documentation, https://github.com/yayami3/py-license-auditor#readme
Project-URL: Issues, https://github.com/yayami3/py-license-auditor/issues
Keywords: license,python,uv,compliance,audit
Classifier: Development Status :: 4 - Beta
Classifier: Intended Audience :: Developers
Classifier: License :: OSI Approved :: MIT License
Classifier: License :: OSI Approved :: Apache Software License
Classifier: Programming Language :: Python :: 3
Classifier: Programming Language :: Rust
Classifier: Topic :: Software Development :: Quality Assurance
Classifier: Topic :: System :: Systems Administration
Requires-Python: >=3.8
License-File: LICENSE-APACHE
License-File: LICENSE-MIT
Dynamic: license-file
